{
  "Organization Details": {
    "Type": "Central Government",
    "Ministry": "Ministry of Defence",
    "Department": "Department of Military Affairs",
    "Organization Name": "Indian Army",
    "Office Zone": "Hq Chief Engineer (r&d) Delhi"
  },
  "Contract Details": {
    "Contract No": "GEMC-511687790007251",
    "Generated Date": "15-Jul-2021"
  },
  "Buyer Details": {
    "Designation": "VARAPRASAD",
    "Contact No": "-7702746650-",
    "Email ID": "prasad140583-cgo@gov.in",
    "GSTIN": "-",
    "Address": "HQ CHIEF ENGINEER RD DELHI BRIG S K MAZUMDAR MARG PROBYN ROAD DELHI-110054, CENTRAL DELHI, DELHI-110054, India"
  },
  "Financial Approval Detail": {
    "IFD Concurrence": "No",
    "Designation of Administrative Approval": "EE",
    "Designation of Financial Approval": "EE"
  },
  "Paying Authority Details": {
    "Role": "",
    "Payment Mode": "Internet Banking",
    "Designation": "GE (I) R&D",
    "Email ID": "deepakk89-cgo@gov.in",
    "GSTIN": "N",
    "Address": "HQ CHIEF ENGINEER RD DELHI BRIG S K MAZUMDAR"
  },
  "Seller Details": {
    "GeM Seller ID": "CFEF180000104336",
    "Company Name": "SHRI BALAJI ENTERPRISES",
    "Contact No": "09891346949",
    "Email ID": "arora_manish83@rediffmail.com",
    "MSME Registration number": "",
    "GSTIN": "07ECLPK4315P1Z3",
    "Address": "C-15,C-15,STREET NO.6,BRAHMPURI ,DELHI-110053,BRAHMPURI"
  },
  "Product Details": {
    "Item Description": "",
    "Product Name": "DEW 900 mm X 450 mm Grade II - Type IV -",
    "Brand": "DEW",
    "Brand Type": "Registered Brand",
    "Catalogue Status": "Catalogue not verified by OEM",
    "Selling As": "Reseller not verified by OEM",
    "Category Name & Quadrant": "",
    "Model": "",
    "HSN Code": "",
    "Ordered Quantity": "",
    "Unit": "",
    "Unit Price (INR)": "900"
  },
  "Consignee Detail": {
    "Designation": "Mahendra Kumar Patra",
    "Email ID": "mkpatra.14267698-cgo@gov.in",
    "Contact": "-",
    "GSTIN": "-",
    "Item": "",
    "Address": "HQ CHIEF ENGINEER RD DELHI BRIG"
  }
}